{"schema":"1.0","catalog":"movie_popular","generatedAt":"2026-04-13T16:17:20Z","page":76,"totalPages":76,"totalItems":150356,"itemsPerPage":2000,"itemsOnPage":356,"hasNext":false,"hasPrev":true,"nextUrl":null,"prevUrl":"https://raw.githubusercontent.com/shadestream/shadestream/master/catalog/movie_popular/page_75.json","items":[{"id":"tt38633147","name":"The Trial of Alec Baldwin","releaseInfo":"2025","imdbRating":"8.5","genres":["Documentary"],"poster":"https://images.metahub.space/poster/small/tt38633147/img","type":"movie"},{"id":"tt38649153","name":"Assassination Classroom the Movie: Our Time","releaseInfo":"2026","imdbRating":"5.6","genres":["Animation","Comedy","Sci-Fi"],"poster":"https://images.metahub.space/poster/small/tt38649153/img","type":"movie"},{"id":"tt38672182","name":"Ella Vive en la Escuela","releaseInfo":"2025","imdbRating":"2.1","genres":["Horror"],"poster":"https://images.metahub.space/poster/small/tt38672182/img","type":"movie"},{"id":"tt38690023","name":"Ajhal","releaseInfo":"2025","imdbRating":"8.1","genres":["Crime","Drama"],"poster":"https://images.metahub.space/poster/small/tt38690023/img","type":"movie"},{"id":"tt38693640","name":"Loyalty and Larceny","releaseInfo":"2026","imdbRating":"9.1","genres":["Thriller"],"poster":"https://images.metahub.space/poster/small/tt38693640/img","type":"movie"},{"id":"tt38693995","name":"Naked Lies","releaseInfo":"2025","imdbRating":"7.4","genres":["Drama"],"poster":"https://images.metahub.space/poster/small/tt38693995/img","type":"movie"},{"id":"tt38755722","name":"The Truth About RFK Jr.","releaseInfo":"2025","imdbRating":"7.0","genres":["Documentary"],"poster":"https://images.metahub.space/poster/small/tt38755722/img","type":"movie"},{"id":"tt38772706","name":"Marjan","releaseInfo":"2025","imdbRating":"1.6","genres":["Drama"],"poster":"https://images.metahub.space/poster/small/tt38772706/img","type":"movie"},{"id":"tt38773974","name":"Snow Beast: Blood Massacre","releaseInfo":"2025","imdbRating":"7.5","genres":["Horror"],"poster":"https://images.metahub.space/poster/small/tt38773974/img","type":"movie"},{"id":"tt38777081","name":"The McFly Story","releaseInfo":"2025","imdbRating":"8.7","genres":["Documentary"],"poster":"https://images.metahub.space/poster/small/tt38777081/img","type":"movie"},{"id":"tt38777426","name":"Three Times","releaseInfo":"2025","imdbRating":"7.0","genres":["Drama"],"poster":"https://images.metahub.space/poster/small/tt38777426/img","type":"movie"},{"id":"tt38778961","name":"The Imaginary Dog and the Lying Cat","releaseInfo":"2025","imdbRating":"6.6","genres":["Drama"],"poster":"https://images.metahub.space/poster/small/tt38778961/img","type":"movie"},{"id":"tt38779928","name":"Alien Arrival the Hidden Past","releaseInfo":"2026","imdbRating":"1.8","genres":["Documentary"],"poster":"https://images.metahub.space/poster/small/tt38779928/img","type":"movie"},{"id":"tt38786229","name":"Go Africa - Skyboy and the Woman of Honor","releaseInfo":"2025","imdbRating":"9.5","genres":["Biography","Drama"],"poster":"https://images.metahub.space/poster/small/tt38786229/img","type":"movie"},{"id":"tt38866965","name":"Todos somos Gaza","releaseInfo":"2025","imdbRating":"5.8","genres":["Documentary"],"poster":"https://images.metahub.space/poster/small/tt38866965/img","type":"movie"},{"id":"tt38872302","name":"Aftershock","releaseInfo":"2025","imdbRating":"8.2","genres":["Drama"],"poster":"https://images.metahub.space/poster/small/tt38872302/img","type":"movie"},{"id":"tt38891401","name":"Roman Gibi","releaseInfo":"2025","imdbRating":"8.8","genres":["Documentary"],"poster":"https://images.metahub.space/poster/small/tt38891401/img","type":"movie"},{"id":"tt38892361","name":"Fractured Island","releaseInfo":"2025","imdbRating":"2.1","genres":["Horror"],"poster":"https://images.metahub.space/poster/small/tt38892361/img","type":"movie"},{"id":"tt38908977","name":"Motu Patlu vs the Ghost House","releaseInfo":"2025","imdbRating":"5.9","genres":["Adventure","Animation","Comedy"],"poster":"https://images.metahub.space/poster/small/tt38908977/img","type":"movie"},{"id":"tt38909406","name":"Dead, White and Blue","releaseInfo":"2025","imdbRating":"5.4","genres":["Action","Comedy","Sci-Fi"],"poster":"https://images.metahub.space/poster/small/tt38909406/img","type":"movie"},{"id":"tt38909526","name":"Breaking Enigma: A World War II Game Changer","releaseInfo":"2025","imdbRating":"6.9","genres":["Documentary","History"],"poster":"https://images.metahub.space/poster/small/tt38909526/img","type":"movie"},{"id":"tt38938232","name":"Sophia","releaseInfo":"2025","imdbRating":"8.4","genres":["Thriller"],"poster":"https://images.metahub.space/poster/small/tt38938232/img","type":"movie"},{"id":"tt38939205","name":"Cards on the Table","releaseInfo":"2025","imdbRating":"9.6","genres":["Comedy","History"],"poster":"https://images.metahub.space/poster/small/tt38939205/img","type":"movie"},{"id":"tt38943005","name":"Weltkarriere einer Lüge - Die Protokolle der Weisen von Zion","releaseInfo":"2025","imdbRating":"7.5","genres":["Documentary"],"poster":"https://images.metahub.space/poster/small/tt38943005/img","type":"movie"},{"id":"tt38945563","name":"The Nonsense","releaseInfo":"2025","imdbRating":"5.4","genres":["Mystery"],"poster":"https://images.metahub.space/poster/small/tt38945563/img","type":"movie"},{"id":"tt39000255","name":"Ibi: Uzay Görevi","releaseInfo":"2025","imdbRating":"4.8","genres":["Animation"],"poster":"https://images.metahub.space/poster/small/tt39000255/img","type":"movie"},{"id":"tt39006162","name":"La Brújula","releaseInfo":"2025","imdbRating":"3.1","genres":["Drama"],"poster":"https://images.metahub.space/poster/small/tt39006162/img","type":"movie"},{"id":"tt39007657","name":"Vikkatakavi - The Movie","releaseInfo":"2025","imdbRating":"4.4","genres":["Drama"],"poster":"https://images.metahub.space/poster/small/tt39007657/img","type":"movie"},{"id":"tt39018561","name":"Sengkolo: The Catastrophe of One Suro","releaseInfo":"2026","imdbRating":"6.8","genres":["Horror"],"poster":"https://images.metahub.space/poster/small/tt39018561/img","type":"movie"},{"id":"tt39034364","name":"Repka: Hrisnik","releaseInfo":"2025","imdbRating":"5.7","genres":[],"poster":"https://images.metahub.space/poster/small/tt39034364/img","type":"movie"},{"id":"tt39078299","name":"EdiblEats","releaseInfo":"2025","imdbRating":"6.1","genres":["Horror"],"poster":"https://images.metahub.space/poster/small/tt39078299/img","type":"movie"},{"id":"tt39127999","name":"Sven de Leijer: Liefde voor Publiek","releaseInfo":"2025","imdbRating":"4.8","genres":["Comedy"],"poster":"https://images.metahub.space/poster/small/tt39127999/img","type":"movie"},{"id":"tt39130987","name":"Stalin's Cola","releaseInfo":"2025","imdbRating":"5.8","genres":["Documentary"],"poster":"https://images.metahub.space/poster/small/tt39130987/img","type":"movie"},{"id":"tt39140112","name":"Véronique","releaseInfo":"2025","imdbRating":"7.5","genres":["Documentary"],"poster":"https://images.metahub.space/poster/small/tt39140112/img","type":"movie"},{"id":"tt39151257","name":"Samuel - L'intégrale de la série","releaseInfo":"2025","imdbRating":"8.0","genres":["Animation","Comedy","Drama"],"poster":"https://images.metahub.space/poster/small/tt39151257/img","type":"movie"},{"id":"tt39158244","name":"Girls Band Cry: The Movie: Youth Rhapsody","releaseInfo":"2025","imdbRating":"7.9","genres":[],"poster":"https://images.metahub.space/poster/small/tt39158244/img","type":"movie"},{"id":"tt39163347","name":"Once Upon a Time in Harlem","releaseInfo":"2026","imdbRating":"8.0","genres":["Documentary"],"poster":"https://images.metahub.space/poster/small/tt39163347/img","type":"movie"},{"id":"tt39172355","name":"The Night Sale","releaseInfo":"2025","imdbRating":"9.1","genres":["Drama"],"poster":"https://images.metahub.space/poster/small/tt39172355/img","type":"movie"},{"id":"tt39177093","name":"The mansion","releaseInfo":"2025","imdbRating":"8.0","genres":["Drama","Fantasy"],"poster":"https://images.metahub.space/poster/small/tt39177093/img","type":"movie"},{"id":"tt39200544","name":"The He Ky Tich","releaseInfo":"2025","imdbRating":"2.5","genres":[],"poster":"https://images.metahub.space/poster/small/tt39200544/img","type":"movie"},{"id":"tt39240447","name":"Love You: Hate You","releaseInfo":"2025","imdbRating":"7.9","genres":["Drama","Romance"],"poster":"https://images.metahub.space/poster/small/tt39240447/img","type":"movie"},{"id":"tt39255149","name":"The Key","releaseInfo":"2025","imdbRating":"8.7","genres":["Comedy","Drama"],"poster":"https://images.metahub.space/poster/small/tt39255149/img","type":"movie"},{"id":"tt39257771","name":"Good Girl, Bad Biker","releaseInfo":"2025","imdbRating":"5.5","genres":["Romance"],"poster":"https://images.metahub.space/poster/small/tt39257771/img","type":"movie"},{"id":"tt39303661","name":"Mondri(a)an","releaseInfo":"2025","imdbRating":"6.0","genres":["Documentary"],"poster":"https://images.metahub.space/poster/small/tt39303661/img","type":"movie"},{"id":"tt39305287","name":"Mo Salah: Never Give Up","releaseInfo":"2025","imdbRating":"7.4","genres":["Sport"],"poster":"https://images.metahub.space/poster/small/tt39305287/img","type":"movie"},{"id":"tt39309765","name":"Basta Mamá","releaseInfo":"2026","imdbRating":"7.6","genres":["Comedy"],"poster":"https://images.metahub.space/poster/small/tt39309765/img","type":"movie"},{"id":"tt39311601","name":"Untouchables: The Story of St. Benedict's Fencing","releaseInfo":"2026","imdbRating":"7.8","genres":["Biography","Documentary"],"poster":"https://images.metahub.space/poster/small/tt39311601/img","type":"movie"},{"id":"tt39372482","name":"Horror Vacui","releaseInfo":"2025","imdbRating":"5.8","genres":["Drama"],"poster":"https://images.metahub.space/poster/small/tt39372482/img","type":"movie"},{"id":"tt39373102","name":"Corriedale: The Omnibus Edition","releaseInfo":"2026","imdbRating":"8.4","genres":["Drama"],"poster":"https://images.metahub.space/poster/small/tt39373102/img","type":"movie"},{"id":"tt39382948","name":"Foreign Travel","releaseInfo":"2026","imdbRating":"5.5","genres":["Drama"],"poster":"https://images.metahub.space/poster/small/tt39382948/img","type":"movie"},{"id":"tt39383458","name":"I Built a Rocket Imagining Your Arrival","releaseInfo":"2026","imdbRating":"6.2","genres":[],"poster":"https://images.metahub.space/poster/small/tt39383458/img","type":"movie"},{"id":"tt39383558","name":"Gemstones","releaseInfo":"2026","imdbRating":"5.2","genres":[],"poster":"https://images.metahub.space/poster/small/tt39383558/img","type":"movie"},{"id":"tt39386635","name":"Las Locas del Obelisco","releaseInfo":"2026","imdbRating":"8.9","genres":["Drama","History"],"poster":"https://images.metahub.space/poster/small/tt39386635/img","type":"movie"},{"id":"tt39389881","name":"The Sin City","releaseInfo":"2026","imdbRating":"5.1","genres":["Action","Crime"],"poster":"https://images.metahub.space/poster/small/tt39389881/img","type":"movie"},{"id":"tt39396713","name":"Matuna Mutton Sikina Chiken","releaseInfo":"2026","imdbRating":"5.9","genres":["Action","Adventure","Comedy"],"poster":"https://images.metahub.space/poster/small/tt39396713/img","type":"movie"},{"id":"tt39539638","name":"Pervaya","releaseInfo":"2026","imdbRating":"6.8","genres":["Drama"],"poster":"https://images.metahub.space/poster/small/tt39539638/img","type":"movie"},{"id":"tt39578289","name":"Baska 2","releaseInfo":"2026","imdbRating":"4.4","genres":["Comedy","Romance"],"poster":"https://images.metahub.space/poster/small/tt39578289/img","type":"movie"},{"id":"tt39674728","name":"Laurita Garza","releaseInfo":"2026","imdbRating":"1.8","genres":["Drama"],"poster":"https://images.metahub.space/poster/small/tt39674728/img","type":"movie"},{"id":"tt39707346","name":"The Block Crew","releaseInfo":"2026","imdbRating":"7.9","genres":["Drama"],"poster":"https://images.metahub.space/poster/small/tt39707346/img","type":"movie"},{"id":"tt39762212","name":"Intelligence Rising","releaseInfo":"2026","imdbRating":"6.4","genres":["Documentary"],"poster":"https://images.metahub.space/poster/small/tt39762212/img","type":"movie"},{"id":"tt39796030","name":"The Death Bath","releaseInfo":"2026","imdbRating":"4.1","genres":["Drama"],"poster":"https://images.metahub.space/poster/small/tt39796030/img","type":"movie"},{"id":"tt39818559","name":"Ozdemir Bayraktar: Bu Dunyadan Bir Akinci Gecti","releaseInfo":"2026","imdbRating":"6.5","genres":["Documentary"],"poster":"https://images.metahub.space/poster/small/tt39818559/img","type":"movie"},{"id":"tt39927766","name":"Beyish 2: Apama kat","releaseInfo":"2026","imdbRating":"9.3","genres":["Adventure","Drama"],"poster":"https://images.metahub.space/poster/small/tt39927766/img","type":"movie"},{"id":"tt39949875","name":"Motel Paradise","releaseInfo":"2026","imdbRating":"1.8","genres":["Documentary"],"poster":"https://images.metahub.space/poster/small/tt39949875/img","type":"movie"},{"id":"tt40029086","name":"Garmi","releaseInfo":"2026","imdbRating":"7.5","genres":["Drama"],"poster":"https://images.metahub.space/poster/small/tt40029086/img","type":"movie"},{"id":"tt40429070","name":"The De4d Echoes","releaseInfo":"2026","imdbRating":"4.2","genres":["Horror"],"poster":"https://images.metahub.space/poster/small/tt40429070/img","type":"movie"},{"id":"tt40444868","name":"James Acaster: Cinemagoers Welcome","releaseInfo":"2026","imdbRating":"8.4","genres":["Documentary"],"poster":"https://images.metahub.space/poster/small/tt40444868/img","type":"movie"},{"id":"tt40887945","name":"PFAS, Our Forever Poisons","releaseInfo":"2026","imdbRating":"7.4","genres":["Documentary"],"poster":"https://images.metahub.space/poster/small/tt40887945/img","type":"movie"},{"id":"tt4548038","name":"Good Tough Kid","releaseInfo":"2025","imdbRating":"9.0","genres":["Biography","Documentary"],"poster":"https://images.metahub.space/poster/small/tt4548038/img","type":"movie"},{"id":"tt6384130","name":"Amílcar","releaseInfo":"2025","imdbRating":"6.7","genres":["Documentary"],"poster":"https://images.metahub.space/poster/small/tt6384130/img","type":"movie"},{"id":"tt7624920","name":"No Means No","releaseInfo":"2025","imdbRating":"6.0","genres":["Action","Drama","Romance"],"poster":"https://images.metahub.space/poster/small/tt7624920/img","type":"movie"},{"id":"tt7696110","name":"The Heart Revolution","releaseInfo":"2025","imdbRating":"8.7","genres":["Documentary"],"poster":"https://images.metahub.space/poster/small/tt7696110/img","type":"movie"},{"id":"tt7852926","name":"Titanic: Kadhalum Kavunthu Pogum","releaseInfo":"2025","imdbRating":"6.0","genres":["Comedy","Romance"],"poster":"https://images.metahub.space/poster/small/tt7852926/img","type":"movie"},{"id":"tt7881534","name":"Danger","releaseInfo":"2025","imdbRating":"4.6","genres":["Horror","Thriller"],"poster":"https://images.metahub.space/poster/small/tt7881534/img","type":"movie"},{"id":"tt9764804","name":"La isla de las Muñecas","releaseInfo":"2026","imdbRating":"8.0","genres":["Horror"],"poster":"https://images.metahub.space/poster/small/tt9764804/img","type":"movie"},{"id":"tt10241002","name":"Marksheet","releaseInfo":"2025","imdbRating":"3.0","genres":["Drama"],"poster":"https://images.metahub.space/poster/small/tt10241002/img","type":"movie"},{"id":"tt11082468","name":"The Gymnast","releaseInfo":"2026","imdbRating":"6.0","genres":["Drama"],"poster":"https://images.metahub.space/poster/small/tt11082468/img","type":"movie"},{"id":"tt11585712","name":"Institute of Pavtollogy","releaseInfo":"2025","imdbRating":"8.0","genres":[],"poster":"https://images.metahub.space/poster/small/tt11585712/img","type":"movie"},{"id":"tt11629874","name":"The Girl in the Feather Jacket","releaseInfo":"2025","imdbRating":"8.8","genres":["Drama"],"poster":"https://images.metahub.space/poster/small/tt11629874/img","type":"movie"},{"id":"tt12689862","name":"Rocky's Galaxy","releaseInfo":"2025","imdbRating":"8.0","genres":["Comedy"],"poster":"https://images.metahub.space/poster/small/tt12689862/img","type":"movie"},{"id":"tt12759038","name":"Ambleside","releaseInfo":"2025","imdbRating":"7.7","genres":["Drama","Romance"],"poster":"https://images.metahub.space/poster/small/tt12759038/img","type":"movie"},{"id":"tt13321796","name":"Luisa","releaseInfo":"2025","imdbRating":"8.2","genres":["Drama"],"poster":"https://images.metahub.space/poster/small/tt13321796/img","type":"movie"},{"id":"tt13521372","name":"Hanak","releaseInfo":"2025","imdbRating":"8.2","genres":["Crime"],"poster":"https://images.metahub.space/poster/small/tt13521372/img","type":"movie"},{"id":"tt13556522","name":"Apne 2","releaseInfo":"2025","imdbRating":"7.2","genres":["Drama"],"poster":"https://images.metahub.space/poster/small/tt13556522/img","type":"movie"},{"id":"tt13839522","name":"The New Jews","releaseInfo":"2025","imdbRating":"5.0","genres":["Documentary"],"poster":"https://images.metahub.space/poster/small/tt13839522/img","type":"movie"},{"id":"tt14940056","name":"The Marianas Web","releaseInfo":"2025","imdbRating":"7.2","genres":["Horror","Sci-Fi","Thriller"],"poster":"https://images.metahub.space/poster/small/tt14940056/img","type":"movie"},{"id":"tt15653280","name":"Clown & Out","releaseInfo":"2026","imdbRating":"6.2","genres":["Adventure","Comedy","Drama"],"poster":"https://images.metahub.space/poster/small/tt15653280/img","type":"movie"},{"id":"tt15709108","name":"Generation Necktie","releaseInfo":"2025","imdbRating":"8.0","genres":["Comedy","Drama"],"poster":"https://images.metahub.space/poster/small/tt15709108/img","type":"movie"},{"id":"tt16756030","name":"Old Man","releaseInfo":"2025","imdbRating":"8.5","genres":[],"poster":"https://images.metahub.space/poster/small/tt16756030/img","type":"movie"},{"id":"tt20202896","name":"Sacred Grounds: Forbidden","releaseInfo":"2025","imdbRating":"7.0","genres":["Adventure","Drama","Thriller"],"poster":"https://images.metahub.space/poster/small/tt20202896/img","type":"movie"},{"id":"tt20518898","name":"Beyond the Wetlands","releaseInfo":"2025","imdbRating":"8.6","genres":["Adventure"],"poster":"https://images.metahub.space/poster/small/tt20518898/img","type":"movie"},{"id":"tt21002048","name":"Queen Evil","releaseInfo":"2025","imdbRating":"3.4","genres":["Drama","Horror"],"poster":"https://images.metahub.space/poster/small/tt21002048/img","type":"movie"},{"id":"tt21917120","name":"The Chocolate Club","releaseInfo":"2025","imdbRating":"5.4","genres":["Romance"],"poster":"https://images.metahub.space/poster/small/tt21917120/img","type":"movie"},{"id":"tt23711138","name":"Rave Culture: A New Era","releaseInfo":"2025","imdbRating":"6.0","genres":["Music"],"poster":"https://images.metahub.space/poster/small/tt23711138/img","type":"movie"},{"id":"tt24801574","name":"Of Mud and Blood","releaseInfo":"2025","imdbRating":"8.0","genres":["Documentary"],"poster":"https://images.metahub.space/poster/small/tt24801574/img","type":"movie"},{"id":"tt26689505","name":"Closure","releaseInfo":"2025","imdbRating":"7.4","genres":["Horror","Mystery"],"poster":"https://images.metahub.space/poster/small/tt26689505/img","type":"movie"},{"id":"tt27137484","name":"Buffalo Daze","releaseInfo":"2025","imdbRating":"5.1","genres":["Drama","Western"],"poster":"https://images.metahub.space/poster/small/tt27137484/img","type":"movie"},{"id":"tt28228275","name":"The Daughters of the Domino","releaseInfo":"2025","imdbRating":"7.7","genres":["Mystery"],"poster":"https://images.metahub.space/poster/small/tt28228275/img","type":"movie"},{"id":"tt28267577","name":"Gowri Shankara","releaseInfo":"2025","imdbRating":"4.9","genres":["Drama"],"poster":"https://images.metahub.space/poster/small/tt28267577/img","type":"movie"},{"id":"tt28353726","name":"The Vessel","releaseInfo":"2025","imdbRating":"6.8","genres":["Horror"],"poster":"https://images.metahub.space/poster/small/tt28353726/img","type":"movie"},{"id":"tt28713543","name":"Nenekkadunna...?","releaseInfo":"2025","imdbRating":"7.4","genres":[],"poster":"https://images.metahub.space/poster/small/tt28713543/img","type":"movie"},{"id":"tt28809566","name":"Riot on Redchurch Street: The Director's Cut","releaseInfo":"2025","imdbRating":"7.7","genres":["Musical"],"poster":"https://images.metahub.space/poster/small/tt28809566/img","type":"movie"},{"id":"tt29377719","name":"Kolai Seval","releaseInfo":"2026","imdbRating":"5.5","genres":[],"poster":"https://images.metahub.space/poster/small/tt29377719/img","type":"movie"},{"id":"tt29382208","name":"Last Stop Video Rentals","releaseInfo":"2025","imdbRating":"6.2","genres":["Comedy"],"poster":"https://images.metahub.space/poster/small/tt29382208/img","type":"movie"},{"id":"tt29498205","name":"Bun Tikki","releaseInfo":"2025","imdbRating":"6.6","genres":["Drama"],"poster":"https://images.metahub.space/poster/small/tt29498205/img","type":"movie"},{"id":"tt29869076","name":"All I Want for Christmas Is You","releaseInfo":"2025","imdbRating":"6.9","genres":["Romance"],"poster":"https://images.metahub.space/poster/small/tt29869076/img","type":"movie"},{"id":"tt29870528","name":"Siksikakowan: The Blackfoot Man","releaseInfo":"2025","imdbRating":"7.7","genres":["Documentary"],"poster":"https://images.metahub.space/poster/small/tt29870528/img","type":"movie"},{"id":"tt30141489","name":"Aranya","releaseInfo":"2025","imdbRating":"7.9","genres":["Drama"],"poster":"https://images.metahub.space/poster/small/tt30141489/img","type":"movie"},{"id":"tt30222867","name":"Thank You for Her","releaseInfo":"2025","imdbRating":"8.5","genres":["Romance"],"poster":"https://images.metahub.space/poster/small/tt30222867/img","type":"movie"},{"id":"tt30224625","name":"Cats in the Museum: Treasures of Egypt","releaseInfo":"2026","imdbRating":"7.1","genres":["Adventure","Animation","Comedy"],"poster":"https://images.metahub.space/poster/small/tt30224625/img","type":"movie"},{"id":"tt30276694","name":"Ping Pong Paradise","releaseInfo":"2025","imdbRating":"7.8","genres":["Documentary"],"poster":"https://images.metahub.space/poster/small/tt30276694/img","type":"movie"},{"id":"tt30294376","name":"Human","releaseInfo":"2025","imdbRating":"6.8","genres":["Horror"],"poster":"https://images.metahub.space/poster/small/tt30294376/img","type":"movie"},{"id":"tt30424259","name":"Kapitan chetvyortogo ranga","releaseInfo":"2025","imdbRating":"7.6","genres":["Comedy","Drama","Romance"],"poster":"https://images.metahub.space/poster/small/tt30424259/img","type":"movie"},{"id":"tt30575879","name":"Cattiva strada","releaseInfo":"2026","imdbRating":"6.9","genres":["Crime"],"poster":"https://images.metahub.space/poster/small/tt30575879/img","type":"movie"},{"id":"tt30759157","name":"Safar Mein Sheher","releaseInfo":"2025","imdbRating":"7.8","genres":["Drama"],"poster":"https://images.metahub.space/poster/small/tt30759157/img","type":"movie"},{"id":"tt30832175","name":"Ishiro Honda: Memoirs of a Film Director","releaseInfo":"2025","imdbRating":"6.6","genres":["Documentary"],"poster":"https://images.metahub.space/poster/small/tt30832175/img","type":"movie"},{"id":"tt30832596","name":"Four Rational People","releaseInfo":"2026","imdbRating":"8.7","genres":["Documentary"],"poster":"https://images.metahub.space/poster/small/tt30832596/img","type":"movie"},{"id":"tt31407172","name":"La fábula de la tortuga y la flor","releaseInfo":"2025","imdbRating":"7.9","genres":["Documentary"],"poster":"https://images.metahub.space/poster/small/tt31407172/img","type":"movie"},{"id":"tt31415510","name":"American Solitaire","releaseInfo":"2025","imdbRating":"7.0","genres":["Drama"],"poster":"https://images.metahub.space/poster/small/tt31415510/img","type":"movie"},{"id":"tt31550000","name":"Revolution 3.0","releaseInfo":"2025","imdbRating":"7.9","genres":["Documentary"],"poster":"https://images.metahub.space/poster/small/tt31550000/img","type":"movie"},{"id":"tt31793957","name":"The Grey Machine","releaseInfo":"2025","imdbRating":"7.2","genres":["Horror"],"poster":"https://images.metahub.space/poster/small/tt31793957/img","type":"movie"},{"id":"tt31850033","name":"Not One Drop of Blood","releaseInfo":"2025","imdbRating":"7.2","genres":["Documentary"],"poster":"https://images.metahub.space/poster/small/tt31850033/img","type":"movie"},{"id":"tt32027860","name":"Office Secrets","releaseInfo":"2025","imdbRating":"9.0","genres":["Drama"],"poster":"https://images.metahub.space/poster/small/tt32027860/img","type":"movie"},{"id":"tt32241947","name":"Clout","releaseInfo":"2025","imdbRating":"8.6","genres":["Drama"],"poster":"https://images.metahub.space/poster/small/tt32241947/img","type":"movie"},{"id":"tt32269291","name":"O Coreto","releaseInfo":"2025","imdbRating":"8.0","genres":["Drama"],"poster":"https://images.metahub.space/poster/small/tt32269291/img","type":"movie"},{"id":"tt32322555","name":"Rhythm Is a Dancer","releaseInfo":"2025","imdbRating":"8.6","genres":["Comedy","Drama"],"poster":"https://images.metahub.space/poster/small/tt32322555/img","type":"movie"},{"id":"tt32411327","name":"Adiós Cuba","releaseInfo":"2025","imdbRating":"8.4","genres":["Drama"],"poster":"https://images.metahub.space/poster/small/tt32411327/img","type":"movie"},{"id":"tt32454557","name":"Full Plate","releaseInfo":"2025","imdbRating":"7.6","genres":["Drama"],"poster":"https://images.metahub.space/poster/small/tt32454557/img","type":"movie"},{"id":"tt32636458","name":"Fall to the Top","releaseInfo":"2025","imdbRating":"7.2","genres":["Action"],"poster":"https://images.metahub.space/poster/small/tt32636458/img","type":"movie"},{"id":"tt32766029","name":"Lost in Territories","releaseInfo":"2025","imdbRating":"4.4","genres":["Comedy","Drama"],"poster":"https://images.metahub.space/poster/small/tt32766029/img","type":"movie"},{"id":"tt32886643","name":"What the Tide Dragged In","releaseInfo":"2025","imdbRating":"5.9","genres":["Drama","Fantasy","Horror"],"poster":"https://images.metahub.space/poster/small/tt32886643/img","type":"movie"},{"id":"tt32986423","name":"Breathe Freedom: the John McNeil story","releaseInfo":"2026","imdbRating":"7.8","genres":["Documentary"],"poster":"https://images.metahub.space/poster/small/tt32986423/img","type":"movie"},{"id":"tt33030511","name":"Astrosphere","releaseInfo":"2026","imdbRating":"6.3","genres":["Sci-Fi"],"poster":"https://images.metahub.space/poster/small/tt33030511/img","type":"movie"},{"id":"tt33040817","name":"Plan C","releaseInfo":"2026","imdbRating":"8.3","genres":["Comedy","Crime","Thriller"],"poster":"https://images.metahub.space/poster/small/tt33040817/img","type":"movie"},{"id":"tt33052652","name":"In the Hands of Fate","releaseInfo":"2025","imdbRating":"7.7","genres":["Crime"],"poster":"https://images.metahub.space/poster/small/tt33052652/img","type":"movie"},{"id":"tt33058435","name":"Guardian","releaseInfo":"2025","imdbRating":"8.0","genres":["Action","Sci-Fi"],"poster":"https://images.metahub.space/poster/small/tt33058435/img","type":"movie"},{"id":"tt33061870","name":"Ambivalence","releaseInfo":"2025","imdbRating":"8.0","genres":["Action","Drama","Thriller"],"poster":"https://images.metahub.space/poster/small/tt33061870/img","type":"movie"},{"id":"tt33145207","name":"Agamemnon","releaseInfo":"2025","imdbRating":"9.8","genres":["Drama"],"poster":"https://images.metahub.space/poster/small/tt33145207/img","type":"movie"},{"id":"tt33395172","name":"The Honeymoon","releaseInfo":"2025","imdbRating":"5.2","genres":["Thriller"],"poster":"https://images.metahub.space/poster/small/tt33395172/img","type":"movie"},{"id":"tt33444507","name":"Nipster","releaseInfo":"2026","imdbRating":"8.8","genres":[],"poster":"https://images.metahub.space/poster/small/tt33444507/img","type":"movie"},{"id":"tt33485500","name":"Zal and Rudaba","releaseInfo":"2025","imdbRating":"3.8","genres":["Fantasy"],"poster":"https://images.metahub.space/poster/small/tt33485500/img","type":"movie"},{"id":"tt33812085","name":"Satchi Perumal (Witness Perumal)","releaseInfo":"2025","imdbRating":"7.4","genres":["Drama"],"poster":"https://images.metahub.space/poster/small/tt33812085/img","type":"movie"},{"id":"tt33945016","name":"120 Days of Sodom Literally","releaseInfo":"2025","imdbRating":"6.6","genres":["Drama"],"poster":"https://images.metahub.space/poster/small/tt33945016/img","type":"movie"},{"id":"tt34243725","name":"Wider than the Sky - Più grande del cielo","releaseInfo":"2025","imdbRating":"6.6","genres":["Documentary"],"poster":"https://images.metahub.space/poster/small/tt34243725/img","type":"movie"},{"id":"tt34266076","name":"Thoughtcrime","releaseInfo":"2025","imdbRating":"7.2","genres":["Documentary"],"poster":"https://images.metahub.space/poster/small/tt34266076/img","type":"movie"},{"id":"tt34279675","name":"The Painter","releaseInfo":"2025","imdbRating":"7.0","genres":["Drama"],"poster":"https://images.metahub.space/poster/small/tt34279675/img","type":"movie"},{"id":"tt34325689","name":"Mirrored Lives","releaseInfo":"2025","imdbRating":"5.0","genres":["Drama"],"poster":"https://images.metahub.space/poster/small/tt34325689/img","type":"movie"},{"id":"tt34359650","name":"Zombucha!","releaseInfo":"2025","imdbRating":"6.9","genres":["Comedy","Sci-Fi"],"poster":"https://images.metahub.space/poster/small/tt34359650/img","type":"movie"},{"id":"tt34460492","name":"Bigfoot vs Megalodon: Resurrection","releaseInfo":"2025","imdbRating":"5.7","genres":["Animation"],"poster":"https://images.metahub.space/poster/small/tt34460492/img","type":"movie"},{"id":"tt34548453","name":"The Hole, 309 Days to the Bloodiest Tragedy","releaseInfo":"2026","imdbRating":"6.0","genres":["Crime","Horror","Mystery"],"poster":"https://images.metahub.space/poster/small/tt34548453/img","type":"movie"},{"id":"tt34625503","name":"Pusherman: Frank Lucas & The True Story of American Gangster","releaseInfo":"2025","imdbRating":"7.0","genres":["Documentary"],"poster":"https://images.metahub.space/poster/small/tt34625503/img","type":"movie"},{"id":"tt34705225","name":"The Council 2","releaseInfo":"2025","imdbRating":"7.8","genres":["Crime"],"poster":"https://images.metahub.space/poster/small/tt34705225/img","type":"movie"},{"id":"tt34748918","name":"Sexa","releaseInfo":"2025","imdbRating":"6.4","genres":["Comedy","Romance"],"poster":"https://images.metahub.space/poster/small/tt34748918/img","type":"movie"},{"id":"tt34766794","name":"On Our Own","releaseInfo":"2026","imdbRating":"6.3","genres":["Drama"],"poster":"https://images.metahub.space/poster/small/tt34766794/img","type":"movie"},{"id":"tt34830382","name":"Priklyucheniya zhyoltogo chemodanchika","releaseInfo":"2026","imdbRating":"7.8","genres":["Adventure","Comedy","Family"],"poster":"https://images.metahub.space/poster/small/tt34830382/img","type":"movie"},{"id":"tt34851715","name":"Die with You","releaseInfo":"2025","imdbRating":"8.1","genres":["Thriller"],"poster":"https://images.metahub.space/poster/small/tt34851715/img","type":"movie"},{"id":"tt34876497","name":"The Line We Crossed","releaseInfo":"2025","imdbRating":"9.4","genres":["Documentary"],"poster":"https://images.metahub.space/poster/small/tt34876497/img","type":"movie"},{"id":"tt34963032","name":"Hamia: Muskanin Cinn-i","releaseInfo":"2025","imdbRating":"2.6","genres":["Horror"],"poster":"https://images.metahub.space/poster/small/tt34963032/img","type":"movie"},{"id":"tt35047940","name":"Serena","releaseInfo":"2026","imdbRating":"9.6","genres":["Thriller"],"poster":"https://images.metahub.space/poster/small/tt35047940/img","type":"movie"},{"id":"tt35048657","name":"P.W.D - Proposal Wedding Divorce (Malayalam)","releaseInfo":"2025","imdbRating":"5.8","genres":["Drama"],"poster":"https://images.metahub.space/poster/small/tt35048657/img","type":"movie"},{"id":"tt35146974","name":"Vermësst!","releaseInfo":"2025","imdbRating":"2.6","genres":["Crime","Drama","Thriller"],"poster":"https://images.metahub.space/poster/small/tt35146974/img","type":"movie"},{"id":"tt35149212","name":"Lonig & Havendel","releaseInfo":"2025","imdbRating":"6.6","genres":["Drama","Fantasy"],"poster":"https://images.metahub.space/poster/small/tt35149212/img","type":"movie"},{"id":"tt35162973","name":"Pintu Ki Pappi","releaseInfo":"2025","imdbRating":"6.1","genres":["Comedy","Drama","Romance"],"poster":"https://images.metahub.space/poster/small/tt35162973/img","type":"movie"},{"id":"tt35255691","name":"Baby Hero","releaseInfo":"2025","imdbRating":"3.2","genres":["Action","Comedy"],"poster":"https://images.metahub.space/poster/small/tt35255691/img","type":"movie"},{"id":"tt35260730","name":"2037","releaseInfo":"2025","imdbRating":"6.3","genres":["Action","Drama","Mystery"],"poster":"https://images.metahub.space/poster/small/tt35260730/img","type":"movie"},{"id":"tt35267732","name":"Modern Women","releaseInfo":"2025","imdbRating":"5.9","genres":["Comedy"],"poster":"https://images.metahub.space/poster/small/tt35267732/img","type":"movie"},{"id":"tt35298996","name":"Scars of a Putsch","releaseInfo":"2025","imdbRating":"7.3","genres":["Documentary"],"poster":"https://images.metahub.space/poster/small/tt35298996/img","type":"movie"},{"id":"tt35318526","name":"Za oponou velehor","releaseInfo":"2025","imdbRating":"7.6","genres":[],"poster":"https://images.metahub.space/poster/small/tt35318526/img","type":"movie"},{"id":"tt35325471","name":"Uh... I'm Sorry, Please Forgive Me","releaseInfo":"2025","imdbRating":"7.3","genres":["Comedy"],"poster":"https://images.metahub.space/poster/small/tt35325471/img","type":"movie"},{"id":"tt35335041","name":"Solo pienso en ti","releaseInfo":"2025","imdbRating":"8.8","genres":["Documentary","Music"],"poster":"https://images.metahub.space/poster/small/tt35335041/img","type":"movie"},{"id":"tt35379536","name":"Nimbiya Banada Myaga - Page - 1","releaseInfo":"2025","imdbRating":"6.1","genres":["Thriller"],"poster":"https://images.metahub.space/poster/small/tt35379536/img","type":"movie"},{"id":"tt35401391","name":"Some Parts Are True","releaseInfo":"2025","imdbRating":"8.4","genres":["Comedy"],"poster":"https://images.metahub.space/poster/small/tt35401391/img","type":"movie"},{"id":"tt35419748","name":"Sauda Khara Khara","releaseInfo":"2025","imdbRating":"4.9","genres":["Comedy"],"poster":"https://images.metahub.space/poster/small/tt35419748/img","type":"movie"},{"id":"tt35457754","name":"Full Figured Flings","releaseInfo":"2026","imdbRating":"9.8","genres":["Drama"],"poster":"https://images.metahub.space/poster/small/tt35457754/img","type":"movie"},{"id":"tt35516431","name":"Heart of A Killer","releaseInfo":"2025","imdbRating":"4.8","genres":["Action"],"poster":"https://images.metahub.space/poster/small/tt35516431/img","type":"movie"},{"id":"tt35522329","name":"Black Storm","releaseInfo":"2025","imdbRating":"8.9","genres":["Action"],"poster":"https://images.metahub.space/poster/small/tt35522329/img","type":"movie"},{"id":"tt35532915","name":"Girl in the closet","releaseInfo":"2025","imdbRating":"4.9","genres":["Action"],"poster":"https://images.metahub.space/poster/small/tt35532915/img","type":"movie"},{"id":"tt35587625","name":"Shapes of Normal Human Beings","releaseInfo":"2025","imdbRating":"7.6","genres":["Documentary"],"poster":"https://images.metahub.space/poster/small/tt35587625/img","type":"movie"},{"id":"tt35603577","name":"Lonely","releaseInfo":"2025","imdbRating":"2.8","genres":["Drama"],"poster":"https://images.metahub.space/poster/small/tt35603577/img","type":"movie"},{"id":"tt35619508","name":"Strandzha","releaseInfo":"2025","imdbRating":"6.3","genres":["Documentary"],"poster":"https://images.metahub.space/poster/small/tt35619508/img","type":"movie"},{"id":"tt35625318","name":"A Song Without Home","releaseInfo":"2026","imdbRating":"8.4","genres":["Documentary"],"poster":"https://images.metahub.space/poster/small/tt35625318/img","type":"movie"},{"id":"tt35652471","name":"Alexandra - Syns vi inte finns vi inte","releaseInfo":"2025","imdbRating":"7.6","genres":["Biography","Documentary"],"poster":"https://images.metahub.space/poster/small/tt35652471/img","type":"movie"},{"id":"tt35661021","name":"No Magic for Socialists","releaseInfo":"2025","imdbRating":"6.3","genres":["Documentary"],"poster":"https://images.metahub.space/poster/small/tt35661021/img","type":"movie"},{"id":"tt35665497","name":"The Last 24","releaseInfo":"2025","imdbRating":"5.4","genres":["Comedy"],"poster":"https://images.metahub.space/poster/small/tt35665497/img","type":"movie"},{"id":"tt35670566","name":"Holka od vedle","releaseInfo":"2025","imdbRating":"5.6","genres":["Comedy","Drama","Romance"],"poster":"https://images.metahub.space/poster/small/tt35670566/img","type":"movie"},{"id":"tt35677391","name":"Fan Girl 2","releaseInfo":"2025","imdbRating":"3.2","genres":[],"poster":"https://images.metahub.space/poster/small/tt35677391/img","type":"movie"},{"id":"tt35679877","name":"Binniza, the Beings of the Clouds","releaseInfo":"2025","imdbRating":"2.8","genres":["Documentary","Fantasy"],"poster":"https://images.metahub.space/poster/small/tt35679877/img","type":"movie"},{"id":"tt35709148","name":"Unpacking the Lies We've Been Fed","releaseInfo":"2025","imdbRating":"7.2","genres":["Documentary"],"poster":"https://images.metahub.space/poster/small/tt35709148/img","type":"movie"},{"id":"tt35710303","name":"Seen the film","releaseInfo":"2025","imdbRating":"9.1","genres":["Documentary"],"poster":"https://images.metahub.space/poster/small/tt35710303/img","type":"movie"},{"id":"tt35851676","name":"Iris","releaseInfo":"2025","imdbRating":"4.6","genres":["Drama","Romance"],"poster":"https://images.metahub.space/poster/small/tt35851676/img","type":"movie"},{"id":"tt35877960","name":"American Theater","releaseInfo":"2025","imdbRating":"6.9","genres":["Documentary"],"poster":"https://images.metahub.space/poster/small/tt35877960/img","type":"movie"},{"id":"tt35891263","name":"The Legend of Sepehr","releaseInfo":"2025","imdbRating":"6.1","genres":["Adventure","Animation"],"poster":"https://images.metahub.space/poster/small/tt35891263/img","type":"movie"},{"id":"tt35933883","name":"Helen David's 37 Seasons","releaseInfo":"2025","imdbRating":"7.4","genres":["Documentary"],"poster":"https://images.metahub.space/poster/small/tt35933883/img","type":"movie"},{"id":"tt35956061","name":"Dolores Ibárruri. Pasionaria","releaseInfo":"2025","imdbRating":"6.8","genres":["Documentary"],"poster":"https://images.metahub.space/poster/small/tt35956061/img","type":"movie"},{"id":"tt35981903","name":"The Degenerate: The Life and Films of Andy Milligan","releaseInfo":"2025","imdbRating":"7.2","genres":["Documentary"],"poster":"https://images.metahub.space/poster/small/tt35981903/img","type":"movie"},{"id":"tt36016579","name":"The Master's Face","releaseInfo":"2025","imdbRating":"3.9","genres":["Horror"],"poster":"https://images.metahub.space/poster/small/tt36016579/img","type":"movie"},{"id":"tt36036792","name":"Return to Homeland","releaseInfo":"2025","imdbRating":"6.3","genres":["Documentary"],"poster":"https://images.metahub.space/poster/small/tt36036792/img","type":"movie"},{"id":"tt36055847","name":"True to Our Inner Daemon","releaseInfo":"2025","imdbRating":"7.9","genres":["Documentary"],"poster":"https://images.metahub.space/poster/small/tt36055847/img","type":"movie"},{"id":"tt36057086","name":"'48: Resisting the Big Settlement","releaseInfo":"2025","imdbRating":"8.1","genres":["Documentary"],"poster":"https://images.metahub.space/poster/small/tt36057086/img","type":"movie"},{"id":"tt36094511","name":"Piercing Screams","releaseInfo":"2025","imdbRating":"7.4","genres":["Horror"],"poster":"https://images.metahub.space/poster/small/tt36094511/img","type":"movie"},{"id":"tt36110964","name":"News Without A Newsroom","releaseInfo":"2025","imdbRating":"8.2","genres":["Documentary"],"poster":"https://images.metahub.space/poster/small/tt36110964/img","type":"movie"},{"id":"tt36119484","name":"Cirkeline & den usynlige tegner","releaseInfo":"2025","imdbRating":"8.2","genres":["Animation","Biography","Documentary"],"poster":"https://images.metahub.space/poster/small/tt36119484/img","type":"movie"},{"id":"tt36157913","name":"Killer Stepdad","releaseInfo":"2025","imdbRating":"6.6","genres":["Thriller"],"poster":"https://images.metahub.space/poster/small/tt36157913/img","type":"movie"},{"id":"tt36316697","name":"Mani 80 pavasari","releaseInfo":"2025","imdbRating":"7.9","genres":["Documentary"],"poster":"https://images.metahub.space/poster/small/tt36316697/img","type":"movie"},{"id":"tt36319065","name":"Archyvu detektyvas","releaseInfo":"2025","imdbRating":"9.8","genres":["Documentary"],"poster":"https://images.metahub.space/poster/small/tt36319065/img","type":"movie"},{"id":"tt36319094","name":"Jacked","releaseInfo":"2025","imdbRating":"6.6","genres":["Thriller"],"poster":"https://images.metahub.space/poster/small/tt36319094/img","type":"movie"},{"id":"tt36330330","name":"Scarecrow","releaseInfo":"2025","imdbRating":"6.3","genres":["Drama"],"poster":"https://images.metahub.space/poster/small/tt36330330/img","type":"movie"},{"id":"tt36353019","name":"Leaving Tallinn. 1941","releaseInfo":"2025","imdbRating":"7.4","genres":["Documentary"],"poster":"https://images.metahub.space/poster/small/tt36353019/img","type":"movie"},{"id":"tt36364096","name":"Upon Her Lips: Girl Power","releaseInfo":"2025","imdbRating":"4.2","genres":["Drama"],"poster":"https://images.metahub.space/poster/small/tt36364096/img","type":"movie"},{"id":"tt36370115","name":"Mariyskie skazki","releaseInfo":"2025","imdbRating":"8.5","genres":["Family","Fantasy"],"poster":"https://images.metahub.space/poster/small/tt36370115/img","type":"movie"},{"id":"tt36454732","name":"Love Live! Nijigasaki High School Idol Club Final Chapter Part 2","releaseInfo":"2025","imdbRating":"5.0","genres":["Animation","Comedy","Music"],"poster":"https://images.metahub.space/poster/small/tt36454732/img","type":"movie"},{"id":"tt36457428","name":"Montevideo Inolvidable","releaseInfo":"2025","imdbRating":"6.2","genres":["Documentary"],"poster":"https://images.metahub.space/poster/small/tt36457428/img","type":"movie"},{"id":"tt36459418","name":"My Dad's Lessons","releaseInfo":"2025","imdbRating":"7.7","genres":["Biography","Documentary"],"poster":"https://images.metahub.space/poster/small/tt36459418/img","type":"movie"},{"id":"tt36508041","name":"Nobody's Coming to Save You","releaseInfo":"2025","imdbRating":"4.9","genres":["Thriller"],"poster":"https://images.metahub.space/poster/small/tt36508041/img","type":"movie"},{"id":"tt36510059","name":"Startup","releaseInfo":"2025","imdbRating":"5.1","genres":["Romance"],"poster":"https://images.metahub.space/poster/small/tt36510059/img","type":"movie"},{"id":"tt36584974","name":"Black Dating","releaseInfo":"2025","imdbRating":"7.4","genres":["Comedy","Drama"],"poster":"https://images.metahub.space/poster/small/tt36584974/img","type":"movie"},{"id":"tt36590996","name":"Jebus","releaseInfo":"2025","imdbRating":"7.5","genres":["Comedy"],"poster":"https://images.metahub.space/poster/small/tt36590996/img","type":"movie"},{"id":"tt36592989","name":"Changed Vol. 2","releaseInfo":"2025","imdbRating":"8.9","genres":["Documentary"],"poster":"https://images.metahub.space/poster/small/tt36592989/img","type":"movie"},{"id":"tt36593056","name":"Hermanos Rivales A Muerte","releaseInfo":"2025","imdbRating":"2.0","genres":["Action","Adventure","Drama"],"poster":"https://images.metahub.space/poster/small/tt36593056/img","type":"movie"},{"id":"tt36596175","name":"Aging in America: Survive or Thrive","releaseInfo":"2025","imdbRating":"8.3","genres":["Documentary"],"poster":"https://images.metahub.space/poster/small/tt36596175/img","type":"movie"},{"id":"tt36599929","name":"Shashtipoorthi","releaseInfo":"2025","imdbRating":"4.2","genres":["Drama","Family"],"poster":"https://images.metahub.space/poster/small/tt36599929/img","type":"movie"},{"id":"tt36687029","name":"The Gloria of Your Imagination","releaseInfo":"2025","imdbRating":"7.9","genres":["Documentary"],"poster":"https://images.metahub.space/poster/small/tt36687029/img","type":"movie"},{"id":"tt36694973","name":"You Are My Son","releaseInfo":"2025","imdbRating":"6.9","genres":["Drama","Family"],"poster":"https://images.metahub.space/poster/small/tt36694973/img","type":"movie"},{"id":"tt36711186","name":"Kurokawa no onna tachi","releaseInfo":"2025","imdbRating":"7.6","genres":["Documentary"],"poster":"https://images.metahub.space/poster/small/tt36711186/img","type":"movie"},{"id":"tt36719463","name":"Tribe","releaseInfo":"2025","imdbRating":"6.1","genres":["Horror"],"poster":"https://images.metahub.space/poster/small/tt36719463/img","type":"movie"},{"id":"tt36874837","name":"My Mother is a Witch","releaseInfo":"2025","imdbRating":"9.4","genres":["Drama"],"poster":"https://images.metahub.space/poster/small/tt36874837/img","type":"movie"},{"id":"tt36881788","name":"Brooker","releaseInfo":"2025","imdbRating":"7.5","genres":["Adventure"],"poster":"https://images.metahub.space/poster/small/tt36881788/img","type":"movie"},{"id":"tt36890106","name":"Mega Trump","releaseInfo":"2025","imdbRating":"5.1","genres":["Animation"],"poster":"https://images.metahub.space/poster/small/tt36890106/img","type":"movie"},{"id":"tt36894412","name":"Cinn-i Zifir","releaseInfo":"2025","imdbRating":"3.2","genres":["Horror"],"poster":"https://images.metahub.space/poster/small/tt36894412/img","type":"movie"},{"id":"tt36907572","name":"Girl, Woman","releaseInfo":"2025","imdbRating":"8.0","genres":["Documentary"],"poster":"https://images.metahub.space/poster/small/tt36907572/img","type":"movie"},{"id":"tt36917030","name":"Szabadság a hegyen","releaseInfo":"2025","imdbRating":"9.0","genres":["Documentary"],"poster":"https://images.metahub.space/poster/small/tt36917030/img","type":"movie"},{"id":"tt36959438","name":"The Chronophage Island","releaseInfo":"2025","imdbRating":"7.6","genres":["Horror","Sci-Fi"],"poster":"https://images.metahub.space/poster/small/tt36959438/img","type":"movie"},{"id":"tt36982066","name":"Condition","releaseInfo":"2025","imdbRating":"7.0","genres":["Mystery"],"poster":"https://images.metahub.space/poster/small/tt36982066/img","type":"movie"},{"id":"tt37020774","name":"Cyclone","releaseInfo":"2026","imdbRating":"6.6","genres":["Drama"],"poster":"https://images.metahub.space/poster/small/tt37020774/img","type":"movie"},{"id":"tt37024922","name":"Amnesia - È Tempo di Dimenticare","releaseInfo":"2025","imdbRating":"7.5","genres":["Mystery","Thriller"],"poster":"https://images.metahub.space/poster/small/tt37024922/img","type":"movie"},{"id":"tt37049970","name":"Citizen of Sun","releaseInfo":"2025","imdbRating":"7.6","genres":["Documentary"],"poster":"https://images.metahub.space/poster/small/tt37049970/img","type":"movie"},{"id":"tt37080702","name":"Torsha Ekti Nodir Naam","releaseInfo":"2025","imdbRating":"6.6","genres":["Family"],"poster":"https://images.metahub.space/poster/small/tt37080702/img","type":"movie"},{"id":"tt37148469","name":"Where Heroes Die","releaseInfo":"2025","imdbRating":"4.1","genres":["Action","Adventure","War"],"poster":"https://images.metahub.space/poster/small/tt37148469/img","type":"movie"},{"id":"tt37197011","name":"Itsanaxa","releaseInfo":"2025","imdbRating":"3.0","genres":[],"poster":"https://images.metahub.space/poster/small/tt37197011/img","type":"movie"},{"id":"tt37274436","name":"Der Donaufürst","releaseInfo":"2025","imdbRating":"9.1","genres":["Animation"],"poster":"https://images.metahub.space/poster/small/tt37274436/img","type":"movie"},{"id":"tt37327827","name":"No Cup, Just Smash!","releaseInfo":"2025","imdbRating":"7.6","genres":["Drama"],"poster":"https://images.metahub.space/poster/small/tt37327827/img","type":"movie"},{"id":"tt37334127","name":"Love and Let Go","releaseInfo":"2025","imdbRating":"5.4","genres":["Drama"],"poster":"https://images.metahub.space/poster/small/tt37334127/img","type":"movie"},{"id":"tt37338216","name":"Crendices - Quando o Medo Vem das Crenças","releaseInfo":"2025","imdbRating":"8.1","genres":["Comedy","Mystery"],"poster":"https://images.metahub.space/poster/small/tt37338216/img","type":"movie"},{"id":"tt37338923","name":"Thrifters","releaseInfo":"2025","imdbRating":"7.1","genres":["Action","Adventure","Comedy"],"poster":"https://images.metahub.space/poster/small/tt37338923/img","type":"movie"},{"id":"tt37341773","name":"Making of an Heiress","releaseInfo":"2025","imdbRating":"8.6","genres":["Drama"],"poster":"https://images.metahub.space/poster/small/tt37341773/img","type":"movie"},{"id":"tt37380555","name":"Fei Chang Jiao Yi","releaseInfo":"2025","imdbRating":"3.2","genres":["Comedy"],"poster":"https://images.metahub.space/poster/small/tt37380555/img","type":"movie"},{"id":"tt37429083","name":"The Old Man and the Parrot","releaseInfo":"2026","imdbRating":"6.2","genres":["Comedy","Drama"],"poster":"https://images.metahub.space/poster/small/tt37429083/img","type":"movie"},{"id":"tt37458189","name":"O Roubo do Cão","releaseInfo":"2025","imdbRating":"6.9","genres":["Comedy"],"poster":"https://images.metahub.space/poster/small/tt37458189/img","type":"movie"},{"id":"tt37538683","name":"Bobò","releaseInfo":"2025","imdbRating":"6.6","genres":["Drama"],"poster":"https://images.metahub.space/poster/small/tt37538683/img","type":"movie"},{"id":"tt37543512","name":"Black Snake","releaseInfo":"2025","imdbRating":"4.9","genres":["Action"],"poster":"https://images.metahub.space/poster/small/tt37543512/img","type":"movie"},{"id":"tt37547195","name":"In a Cold Vein","releaseInfo":"2025","imdbRating":"6.4","genres":["Crime","Thriller"],"poster":"https://images.metahub.space/poster/small/tt37547195/img","type":"movie"},{"id":"tt37592938","name":"The Dreamer","releaseInfo":"2025","imdbRating":"6.8","genres":["Documentary"],"poster":"https://images.metahub.space/poster/small/tt37592938/img","type":"movie"},{"id":"tt37674717","name":"Paris 75: The European Cup Final Football Tried to Forget","releaseInfo":"2025","imdbRating":"7.7","genres":["Documentary"],"poster":"https://images.metahub.space/poster/small/tt37674717/img","type":"movie"},{"id":"tt37674762","name":"CORAZON DE CAMPEON (Chavez Vs Paez)","releaseInfo":"2025","imdbRating":"2.5","genres":["History"],"poster":"https://images.metahub.space/poster/small/tt37674762/img","type":"movie"},{"id":"tt37679066","name":"Dinosaur Hunt","releaseInfo":"2026","imdbRating":"4.2","genres":["Horror"],"poster":"https://images.metahub.space/poster/small/tt37679066/img","type":"movie"},{"id":"tt37741683","name":"Bad Choices 2","releaseInfo":"2025","imdbRating":"8.4","genres":["Drama"],"poster":"https://images.metahub.space/poster/small/tt37741683/img","type":"movie"},{"id":"tt37813085","name":"Palimpsest: The Story of a Name","releaseInfo":"2025","imdbRating":"7.5","genres":["Biography","Documentary","History"],"poster":"https://images.metahub.space/poster/small/tt37813085/img","type":"movie"},{"id":"tt37844755","name":"Mrigatrishna","releaseInfo":"2025","imdbRating":"5.6","genres":["Mystery"],"poster":"https://images.metahub.space/poster/small/tt37844755/img","type":"movie"},{"id":"tt37845067","name":"Mihira","releaseInfo":"2025","imdbRating":"7.2","genres":["Drama"],"poster":"https://images.metahub.space/poster/small/tt37845067/img","type":"movie"},{"id":"tt37896286","name":"Kaptan Pengu ve Arkadaslari 5","releaseInfo":"2025","imdbRating":"5.1","genres":[],"poster":"https://images.metahub.space/poster/small/tt37896286/img","type":"movie"},{"id":"tt37898765","name":"Reinas de la Noche","releaseInfo":"2025","imdbRating":"5.4","genres":[],"poster":"https://images.metahub.space/poster/small/tt37898765/img","type":"movie"},{"id":"tt37899555","name":"I: Scream- A Minty Musical","releaseInfo":"2025","imdbRating":"5.6","genres":["Musical","Sci-Fi"],"poster":"https://images.metahub.space/poster/small/tt37899555/img","type":"movie"},{"id":"tt37919188","name":"Riding with Death","releaseInfo":"2025","imdbRating":"7.3","genres":["Documentary"],"poster":"https://images.metahub.space/poster/small/tt37919188/img","type":"movie"},{"id":"tt37953484","name":"Those Who Say No!","releaseInfo":"2025","imdbRating":"1.8","genres":["Documentary"],"poster":"https://images.metahub.space/poster/small/tt37953484/img","type":"movie"},{"id":"tt37954397","name":"Heroic Cadets","releaseInfo":"2025","imdbRating":"1.7","genres":["Documentary"],"poster":"https://images.metahub.space/poster/small/tt37954397/img","type":"movie"},{"id":"tt37958765","name":"Doctor Gaf","releaseInfo":"2026","imdbRating":"9.0","genres":["Adventure","Comedy","Family"],"poster":"https://images.metahub.space/poster/small/tt37958765/img","type":"movie"},{"id":"tt37995676","name":"Devangana","releaseInfo":"2025","imdbRating":"5.2","genres":["Drama"],"poster":"https://images.metahub.space/poster/small/tt37995676/img","type":"movie"},{"id":"tt38070369","name":"Danny Is My Boyfriend","releaseInfo":"2025","imdbRating":"7.0","genres":["Comedy"],"poster":"https://images.metahub.space/poster/small/tt38070369/img","type":"movie"},{"id":"tt38073061","name":"Golden Brothers 2","releaseInfo":"2025","imdbRating":"6.5","genres":["Action","Comedy","Drama"],"poster":"https://images.metahub.space/poster/small/tt38073061/img","type":"movie"},{"id":"tt38077025","name":"Thunderbirds: Fab at 60","releaseInfo":"2025","imdbRating":"7.9","genres":["Documentary"],"poster":"https://images.metahub.space/poster/small/tt38077025/img","type":"movie"},{"id":"tt38119124","name":"Syurga Dalam Botol","releaseInfo":"2025","imdbRating":"5.9","genres":[],"poster":"https://images.metahub.space/poster/small/tt38119124/img","type":"movie"},{"id":"tt38120535","name":"Crystal Cross","releaseInfo":"2025","imdbRating":"8.9","genres":["Comedy"],"poster":"https://images.metahub.space/poster/small/tt38120535/img","type":"movie"},{"id":"tt38124241","name":"More Life","releaseInfo":"2025","imdbRating":"3.4","genres":["Comedy"],"poster":"https://images.metahub.space/poster/small/tt38124241/img","type":"movie"},{"id":"tt38128163","name":"Pan Olbrychski","releaseInfo":"2025","imdbRating":"7.3","genres":["Biography","Documentary"],"poster":"https://images.metahub.space/poster/small/tt38128163/img","type":"movie"},{"id":"tt38266699","name":"Alkarisi 2","releaseInfo":"2025","imdbRating":"2.2","genres":[],"poster":"https://images.metahub.space/poster/small/tt38266699/img","type":"movie"},{"id":"tt38355154","name":"If on a Winter's Night","releaseInfo":"2025","imdbRating":"6.0","genres":["Drama","Romance"],"poster":"https://images.metahub.space/poster/small/tt38355154/img","type":"movie"},{"id":"tt38411390","name":"The Bouzaglos: The Battle for the Inheritance","releaseInfo":"2025","imdbRating":"5.7","genres":["Comedy"],"poster":"https://images.metahub.space/poster/small/tt38411390/img","type":"movie"},{"id":"tt38428501","name":"Pop","releaseInfo":"2025","imdbRating":"6.5","genres":["Adventure","Comedy","Music"],"poster":"https://images.metahub.space/poster/small/tt38428501/img","type":"movie"},{"id":"tt38448241","name":"Wrangler","releaseInfo":"2025","imdbRating":"5.9","genres":["Drama","Thriller"],"poster":"https://images.metahub.space/poster/small/tt38448241/img","type":"movie"},{"id":"tt38492520","name":"Tugan Batyr","releaseInfo":"2025","imdbRating":"6.1","genres":["Adventure","Animation","Family"],"poster":"https://images.metahub.space/poster/small/tt38492520/img","type":"movie"},{"id":"tt38494621","name":"In Passing","releaseInfo":"2025","imdbRating":"8.6","genres":["Documentary"],"poster":"https://images.metahub.space/poster/small/tt38494621/img","type":"movie"},{"id":"tt38497662","name":"Honestino","releaseInfo":"2025","imdbRating":"5.8","genres":["Documentary"],"poster":"https://images.metahub.space/poster/small/tt38497662/img","type":"movie"},{"id":"tt38566480","name":"Prisutstvie","releaseInfo":"2025","imdbRating":"7.8","genres":["Horror","Thriller"],"poster":"https://images.metahub.space/poster/small/tt38566480/img","type":"movie"},{"id":"tt38587950","name":"Blonde","releaseInfo":"2025","imdbRating":"5.9","genres":["Drama"],"poster":"https://images.metahub.space/poster/small/tt38587950/img","type":"movie"},{"id":"tt38588549","name":"Az Eshgh","releaseInfo":"2025","imdbRating":"1.6","genres":["Drama","Romance"],"poster":"https://images.metahub.space/poster/small/tt38588549/img","type":"movie"},{"id":"tt38589433","name":"Never After Dark","releaseInfo":"2026","imdbRating":"8.4","genres":["Horror"],"poster":"https://images.metahub.space/poster/small/tt38589433/img","type":"movie"},{"id":"tt38593970","name":"Zusammen ist man weniger getrennt.","releaseInfo":"2025","imdbRating":"8.9","genres":["Comedy"],"poster":"https://images.metahub.space/poster/small/tt38593970/img","type":"movie"},{"id":"tt38624696","name":"The Last Checkpoint: A Roblox Movie","releaseInfo":"2025","imdbRating":"6.6","genres":["Action","Adventure","Animation"],"poster":"https://images.metahub.space/poster/small/tt38624696/img","type":"movie"},{"id":"tt38632055","name":"Seragu","releaseInfo":"2025","imdbRating":"6.9","genres":["Drama"],"poster":"https://images.metahub.space/poster/small/tt38632055/img","type":"movie"},{"id":"tt38639850","name":"I Love Lucca Comics & Games","releaseInfo":"2025","imdbRating":"6.7","genres":["Documentary"],"poster":"https://images.metahub.space/poster/small/tt38639850/img","type":"movie"},{"id":"tt38651269","name":"The Woman Who Poked the Leopard","releaseInfo":"2025","imdbRating":"7.4","genres":["Documentary"],"poster":"https://images.metahub.space/poster/small/tt38651269/img","type":"movie"},{"id":"tt38672229","name":"Game Khatam","releaseInfo":"2025","imdbRating":"7.9","genres":["Action","Crime","Thriller"],"poster":"https://images.metahub.space/poster/small/tt38672229/img","type":"movie"},{"id":"tt38672900","name":"Senden Kalan","releaseInfo":"2025","imdbRating":"5.7","genres":["Drama"],"poster":"https://images.metahub.space/poster/small/tt38672900/img","type":"movie"},{"id":"tt38681496","name":"Sai: Disaster","releaseInfo":"2025","imdbRating":"7.2","genres":["Horror","Thriller"],"poster":"https://images.metahub.space/poster/small/tt38681496/img","type":"movie"},{"id":"tt38690060","name":"The Kartli Kingdom","releaseInfo":"2025","imdbRating":"8.6","genres":["Documentary"],"poster":"https://images.metahub.space/poster/small/tt38690060/img","type":"movie"},{"id":"tt38715684","name":"The Birth of Your Divinity","releaseInfo":"2025","imdbRating":"9.1","genres":["Documentary"],"poster":"https://images.metahub.space/poster/small/tt38715684/img","type":"movie"},{"id":"tt38716049","name":"The Grail Code - Revelation Zero","releaseInfo":"2025","imdbRating":"9.4","genres":[],"poster":"https://images.metahub.space/poster/small/tt38716049/img","type":"movie"},{"id":"tt38734796","name":"When Nobody's Watching","releaseInfo":"2025","imdbRating":"7.9","genres":["Documentary"],"poster":"https://images.metahub.space/poster/small/tt38734796/img","type":"movie"},{"id":"tt38740515","name":"Unicorn Born of Light","releaseInfo":"2025","imdbRating":"4.1","genres":["Animation"],"poster":"https://images.metahub.space/poster/small/tt38740515/img","type":"movie"},{"id":"tt38743588","name":"Our Body Is an Expanding Star","releaseInfo":"2025","imdbRating":"2.8","genres":["Documentary"],"poster":"https://images.metahub.space/poster/small/tt38743588/img","type":"movie"},{"id":"tt38783848","name":"Kosmos","releaseInfo":"2025","imdbRating":"7.9","genres":["Documentary"],"poster":"https://images.metahub.space/poster/small/tt38783848/img","type":"movie"},{"id":"tt38790586","name":"Mountains of the Moon","releaseInfo":"2025","imdbRating":"8.9","genres":["Documentary","Music","Sport"],"poster":"https://images.metahub.space/poster/small/tt38790586/img","type":"movie"},{"id":"tt38795533","name":"Winter Sea","releaseInfo":"2025","imdbRating":"7.7","genres":["Drama"],"poster":"https://images.metahub.space/poster/small/tt38795533/img","type":"movie"},{"id":"tt38796175","name":"Die by Law","releaseInfo":"2025","imdbRating":"5.9","genres":["Action","Crime","Drama"],"poster":"https://images.metahub.space/poster/small/tt38796175/img","type":"movie"},{"id":"tt38854615","name":"Admission","releaseInfo":"2025","imdbRating":"7.6","genres":["Drama"],"poster":"https://images.metahub.space/poster/small/tt38854615/img","type":"movie"},{"id":"tt38866243","name":"Quy tha ma bat: Thai chieu tai","releaseInfo":"2025","imdbRating":"7.2","genres":["Drama","Horror"],"poster":"https://images.metahub.space/poster/small/tt38866243/img","type":"movie"},{"id":"tt38876318","name":"Trai Tim Que Quat","releaseInfo":"2025","imdbRating":"6.9","genres":["Crime","Drama","Thriller"],"poster":"https://images.metahub.space/poster/small/tt38876318/img","type":"movie"},{"id":"tt38884324","name":"Sang Rah (Stone Lane)","releaseInfo":"2025","imdbRating":"1.8","genres":["Adventure","Drama","Horror"],"poster":"https://images.metahub.space/poster/small/tt38884324/img","type":"movie"},{"id":"tt38934572","name":"Ai Thuong Ai Men","releaseInfo":"2026","imdbRating":"4.1","genres":["Comedy","Drama"],"poster":"https://images.metahub.space/poster/small/tt38934572/img","type":"movie"},{"id":"tt38953112","name":"Risha","releaseInfo":"2025","imdbRating":"9.6","genres":["Documentary"],"poster":"https://images.metahub.space/poster/small/tt38953112/img","type":"movie"},{"id":"tt38988300","name":"School Chale Hum","releaseInfo":"2025","imdbRating":"8.0","genres":["Drama","Fantasy"],"poster":"https://images.metahub.space/poster/small/tt38988300/img","type":"movie"},{"id":"tt39000852","name":"El Selem W El Thoban","releaseInfo":"2025","imdbRating":"5.0","genres":[],"poster":"https://images.metahub.space/poster/small/tt39000852/img","type":"movie"},{"id":"tt39028290","name":"Notes from the Woods","releaseInfo":"2025","imdbRating":"8.4","genres":["Documentary"],"poster":"https://images.metahub.space/poster/small/tt39028290/img","type":"movie"},{"id":"tt39029586","name":"Agesinkole 2: King of Thieves","releaseInfo":"2025","imdbRating":"8.7","genres":["Action"],"poster":"https://images.metahub.space/poster/small/tt39029586/img","type":"movie"},{"id":"tt39045202","name":"Rappa Roy & Full Stop Dot Com","releaseInfo":"2025","imdbRating":"7.1","genres":["Action","Comedy","Romance"],"poster":"https://images.metahub.space/poster/small/tt39045202/img","type":"movie"},{"id":"tt39061882","name":"Gotya Gangster","releaseInfo":"2025","imdbRating":"4.2","genres":["Comedy","Crime","Drama"],"poster":"https://images.metahub.space/poster/small/tt39061882/img","type":"movie"},{"id":"tt39139779","name":"Ekhane Rajnoitik Alap Joruri","releaseInfo":"2026","imdbRating":"4.0","genres":["Drama"],"poster":"https://images.metahub.space/poster/small/tt39139779/img","type":"movie"},{"id":"tt39292520","name":"What Shall We Dream Of","releaseInfo":"2026","imdbRating":"6.9","genres":["Drama"],"poster":"https://images.metahub.space/poster/small/tt39292520/img","type":"movie"},{"id":"tt39300414","name":"In search of treasures","releaseInfo":"2025","imdbRating":"7.8","genres":["Documentary"],"poster":"https://images.metahub.space/poster/small/tt39300414/img","type":"movie"},{"id":"tt39300443","name":"In search of treasures 2","releaseInfo":"2025","imdbRating":"7.8","genres":["Documentary"],"poster":"https://images.metahub.space/poster/small/tt39300443/img","type":"movie"},{"id":"tt39316737","name":"FA Cup: The People's Story","releaseInfo":"2026","imdbRating":"8.8","genres":["Documentary"],"poster":"https://images.metahub.space/poster/small/tt39316737/img","type":"movie"},{"id":"tt39318415","name":"Everyday, We Are","releaseInfo":"2026","imdbRating":"6.0","genres":["Drama","Romance"],"poster":"https://images.metahub.space/poster/small/tt39318415/img","type":"movie"},{"id":"tt39358084","name":"Lulk","releaseInfo":"2026","imdbRating":"8.2","genres":["Comedy","Crime"],"poster":"https://images.metahub.space/poster/small/tt39358084/img","type":"movie"},{"id":"tt39368474","name":"Black Zombie","releaseInfo":"2026","imdbRating":"9.6","genres":["Documentary","History","Horror"],"poster":"https://images.metahub.space/poster/small/tt39368474/img","type":"movie"},{"id":"tt39370389","name":"The Hunt","releaseInfo":"2026","imdbRating":"7.0","genres":["Horror"],"poster":"https://images.metahub.space/poster/small/tt39370389/img","type":"movie"},{"id":"tt39371375","name":"Not a Hero","releaseInfo":"2026","imdbRating":"6.9","genres":["Drama"],"poster":"https://images.metahub.space/poster/small/tt39371375/img","type":"movie"},{"id":"tt39383353","name":"Collapse","releaseInfo":"2026","imdbRating":"8.5","genres":["Documentary"],"poster":"https://images.metahub.space/poster/small/tt39383353/img","type":"movie"},{"id":"tt39388742","name":"Sovereign Son","releaseInfo":"2026","imdbRating":"9.5","genres":["Documentary"],"poster":"https://images.metahub.space/poster/small/tt39388742/img","type":"movie"},{"id":"tt39514054","name":"Dabesh","releaseInfo":"2026","imdbRating":"7.2","genres":["Action","Crime"],"poster":"https://images.metahub.space/poster/small/tt39514054/img","type":"movie"},{"id":"tt39674633","name":"Seule la tendresse","releaseInfo":"2026","imdbRating":"6.2","genres":[],"poster":"https://images.metahub.space/poster/small/tt39674633/img","type":"movie"},{"id":"tt39793111","name":"Whispers in May","releaseInfo":"2026","imdbRating":"7.5","genres":["Documentary"],"poster":"https://images.metahub.space/poster/small/tt39793111/img","type":"movie"},{"id":"tt39796063","name":"Ordoobehesht","releaseInfo":"2026","imdbRating":"4.6","genres":[],"poster":"https://images.metahub.space/poster/small/tt39796063/img","type":"movie"},{"id":"tt39798962","name":"Minecraft Movie Edition","releaseInfo":"2026","imdbRating":"5.2","genres":["Fantasy"],"poster":"https://images.metahub.space/poster/small/tt39798962/img","type":"movie"},{"id":"tt39846658","name":"Not Welcome: The Battle to Stop the Boats","releaseInfo":"2026","imdbRating":"6.0","genres":["Documentary"],"poster":"https://images.metahub.space/poster/small/tt39846658/img","type":"movie"},{"id":"tt39948152","name":"Hex","releaseInfo":"2026","imdbRating":"6.2","genres":["Documentary","Music"],"poster":"https://images.metahub.space/poster/small/tt39948152/img","type":"movie"},{"id":"tt39949871","name":"Just Look Up","releaseInfo":"2026","imdbRating":"9.0","genres":["Documentary"],"poster":"https://images.metahub.space/poster/small/tt39949871/img","type":"movie"},{"id":"tt39955176","name":"Büyü 3: Son Ayin","releaseInfo":"2026","imdbRating":"2.9","genres":["Horror"],"poster":"https://images.metahub.space/poster/small/tt39955176/img","type":"movie"},{"id":"tt40108676","name":"Offline","releaseInfo":"2026","imdbRating":"9.1","genres":["Thriller"],"poster":"https://images.metahub.space/poster/small/tt40108676/img","type":"movie"},{"id":"tt40163844","name":"For the Love of Gold","releaseInfo":"2026","imdbRating":"9.1","genres":["Comedy"],"poster":"https://images.metahub.space/poster/small/tt40163844/img","type":"movie"},{"id":"tt40398957","name":"Game Start","releaseInfo":"2026","imdbRating":"6.8","genres":["Drama","Thriller"],"poster":"https://images.metahub.space/poster/small/tt40398957/img","type":"movie"},{"id":"tt40554259","name":"Conscious","releaseInfo":"2026","imdbRating":"9.6","genres":["Documentary"],"poster":"https://images.metahub.space/poster/small/tt40554259/img","type":"movie"},{"id":"tt40671062","name":"Mann Pishach","releaseInfo":"2026","imdbRating":"5.2","genres":[],"poster":"https://images.metahub.space/poster/small/tt40671062/img","type":"movie"},{"id":"tt40726801","name":"Lo que intentamos ser.","releaseInfo":"2026","imdbRating":"1.0","genres":["Comedy","Drama","Romance"],"poster":"https://images.metahub.space/poster/small/tt40726801/img","type":"movie"},{"id":"tt40836029","name":"Escalofrío","releaseInfo":"2026","imdbRating":"1.0","genres":["Action"],"poster":"https://images.metahub.space/poster/small/tt40836029/img","type":"movie"},{"id":"tt40868369","name":"Invisible Enemy","releaseInfo":"2026","imdbRating":"7.5","genres":["Documentary"],"poster":"https://images.metahub.space/poster/small/tt40868369/img","type":"movie"},{"id":"tt41041551","name":"The Email","releaseInfo":"2026","imdbRating":"5.9","genres":["Drama"],"poster":"https://images.metahub.space/poster/small/tt41041551/img","type":"movie"},{"id":"tt41425495","name":"Hasta que amanezca","releaseInfo":"2026","imdbRating":"4.6","genres":["Comedy"],"poster":"https://images.metahub.space/poster/small/tt41425495/img","type":"movie"},{"id":"tt5258930","name":"Dziennik z wycieczki do Budapesztu","releaseInfo":"2025","imdbRating":"6.9","genres":["Drama"],"poster":"https://images.metahub.space/poster/small/tt5258930/img","type":"movie"},{"id":"tt5699416","name":"Ambrosia","releaseInfo":"2025","imdbRating":"6.1","genres":["Adventure","Fantasy","History"],"poster":"https://images.metahub.space/poster/small/tt5699416/img","type":"movie"},{"id":"tt6352510","name":"The Last Partera","releaseInfo":"2025","imdbRating":"9.0","genres":["Documentary"],"poster":"https://images.metahub.space/poster/small/tt6352510/img","type":"movie"},{"id":"tt6802432","name":"Papagaios","releaseInfo":"2025","imdbRating":"7.8","genres":["Crime","Thriller"],"poster":"https://images.metahub.space/poster/small/tt6802432/img","type":"movie"},{"id":"tt7415596","name":"Girassol Vermelho","releaseInfo":"2025","imdbRating":"8.8","genres":["Drama","Fantasy"],"poster":"https://images.metahub.space/poster/small/tt7415596/img","type":"movie"},{"id":"tt7719328","name":"Man's Game","releaseInfo":"2026","imdbRating":"9.8","genres":["Drama"],"poster":"https://images.metahub.space/poster/small/tt7719328/img","type":"movie"},{"id":"tt7740330","name":"Nuptials","releaseInfo":"2026","imdbRating":"4.6","genres":["Drama","Horror","Romance"],"poster":"https://images.metahub.space/poster/small/tt7740330/img","type":"movie"},{"id":"tt7991490","name":"A Little Fellow: The Legacy of A.P. Giannini","releaseInfo":"2025","imdbRating":"8.9","genres":["Documentary"],"poster":"https://images.metahub.space/poster/small/tt7991490/img","type":"movie"},{"id":"tt8665458","name":"Surfacing","releaseInfo":"2026","imdbRating":"9.0","genres":["Drama","Romance"],"poster":"https://images.metahub.space/poster/small/tt8665458/img","type":"movie"}]}